justgood/__init__.py
justgood/justgood.py
justgood-2.3.0.dist-info/LICENSE
justgood-2.3.0.dist-info/METADATA
justgood-2.3.0.dist-info/WHEEL
justgood-2.3.0.dist-info/entry_points.txt
justgood-2.3.0.dist-info/top_level.txt
justgood-2.3.0.dist-info/RECORD
