Metadata-Version: 2.1
Name: justgood
Version: 2.3.0
Summary: Sample request for api.imjustgood.com please visit webpage imjustgood.com for more details
Home-page: https://github.com/RendyTR/api.imjustgood.com
Author: Yoshino
Author-email: admin@imjustgood.com
License: MIT
Classifier: License :: OSI Approved :: MIT License
Classifier: Programming Language :: Python :: 3
Classifier: Programming Language :: Python :: 3.6
Classifier: Programming Language :: Python :: 3.7
License-File: LICENSE
